[{"model": "fileApp.engineeringassignment", "pk": 1144, "fields": {"base_name": "alp%20reno%202011.pdf", "file": 51959, "grid_cell": "L21", "date_assigned": "2017-10-16", "comment": ""}}, {"model": "fileApp.engineeringassignment", "pk": 1145, "fields": {"base_name": "alp%20reno%202011.pdf", "file": 51959, "grid_cell": "L22", "date_assigned": "2017-10-16", "comment": ""}}, {"model": "fileApp.engineeringassignment", "pk": 1146, "fields": {"base_name": "alp%20reno%202011.pdf", "file": 51959, "grid_cell": "M21", "date_assigned": "2017-10-16", "comment": ""}}, {"model": "fileApp.engineeringassignment", "pk": 1147, "fields": {"base_name": "alp%20reno%202011.pdf", "file": 51959, "grid_cell": "M22", "date_assigned": "2017-10-16", "comment": ""}}]