[{"fields": {}, "pk": "A01", "model": "fileApp.gridcell"}, {"fields": {}, "pk": "A02", "model": "fileApp.gridcell"}, {"fields": {}, "pk": "A03", "model": "fileApp.gridcell"}, {"fields": {}, "pk": "A04", "model": "fileApp.gridcell"}, {"fields": {}, "pk": "A05", "model": "fileApp.gridcell"}, {"fields": {}, "pk": "A06", "model": "fileApp.gridcell"}, {"fields": {}, "pk": "A07", "model": "fileApp.gridcell"}, {"fields": {}, "pk": "A08", "model": "fileApp.gridcell"}, {"fields": {}, "pk": "A09", "model": "fileApp.gridcell"}, {"fields": {}, "pk": "A10", "model": "fileApp.gridcell"}, {"fields": {}, "pk": "A11", "model": "fileApp.gridcell"}, {"fields": {}, "pk": "A12", "model": "fileApp.gridcell"}, {"fields": {}, "pk": "A13", "model": "fileApp.gridcell"}, {"fields": {}, "pk": "A14", "model": "fileApp.gridcell"}, {"fields": {}, "pk": "A15", "model": "fileApp.gridcell"}, {"fields": {}, "pk": "A16", "model": "fileApp.gridcell"}, {"fields": {}, "pk": "A17", "model": "fileApp.gridcell"}, {"fields": {}, "pk": "A18", "model": "fileApp.gridcell"}, {"fields": {}, "pk": "A19", "model": "fileApp.gridcell"}, {"fields": {}, "pk": "A20", "model": "fileApp.gridcell"}, {"fields": {}, "pk": "A21", "model": "fileApp.gridcell"}, {"fields": {}, "pk": "A22", "model": "fileApp.gridcell"}, {"fields": {}, "pk": "A23", "model": "fileApp.gridcell"}, {"fields": {}, "pk": "A24", "model": "fileApp.gridcell"}, {"fields": {}, "pk": "A25", "model": "fileApp.gridcell"}, {"fields": {}, "pk": "A26", "model": "fileApp.gridcell"}, {"fields": {}, "pk": "A27", "model": "fileApp.gridcell"}, {"fields": {}, "pk": "A28", "model": "fileApp.gridcell"}, {"fields": {}, "pk": "A29", "model": "fileApp.gridcell"}, {"fields": {}, "pk": "A30", "model": "fileApp.gridcell"}, {"fields": {}, "pk": "A31", "model": "fileApp.gridcell"}, {"fields": {}, "pk": "A32", "model": "fileApp.gridcell"}, {"fields": {}, "pk": "A33", "model": "fileApp.gridcell"}, {"fields": {}, "pk": "A34", "model": "fileApp.gridcell"}, {"fields": {}, "pk": "A35", "model": "fileApp.gridcell"}, {"fields": {}, "pk": "A36", "model": "fileApp.gridcell"}, {"fields": {}, "pk": "A37", "model": "fileApp.gridcell"}, {"fields": {}, "pk": "A38", "model": "fileApp.gridcell"}, {"fields": {}, "pk": "A39", "model": "fileApp.gridcell"}, {"fields": {}, "pk": "A40", "model": "fileApp.gridcell"}, {"fields": {}, "pk": "A41", "model": "fileApp.gridcell"}, {"fields": {}, "pk": "A42", "model": "fileApp.gridcell"}, {"fields": {}, "pk": "A43", "model": "fileApp.gridcell"}, {"fields": {}, "pk": "A44", "model": "fileApp.gridcell"}, {"fields": {}, "pk": "B01", "model": "fileApp.gridcell"}, {"fields": {}, "pk": "B02", "model": "fileApp.gridcell"}, {"fields": {}, "pk": "B03", "model": "fileApp.gridcell"}, {"fields": {}, "pk": "B04", "model": "fileApp.gridcell"}, {"fields": {}, "pk": "B05", "model": "fileApp.gridcell"}, {"fields": {}, "pk": "B06", "model": "fileApp.gridcell"}, {"fields": {}, "pk": "B07", "model": "fileApp.gridcell"}, {"fields": {}, "pk": "B08", "model": "fileApp.gridcell"}, {"fields": {}, "pk": "B09", "model": "fileApp.gridcell"}, {"fields": {}, "pk": "B10", "model": "fileApp.gridcell"}, {"fields": {}, "pk": "B11", "model": "fileApp.gridcell"}, {"fields": {}, "pk": "B12", "model": "fileApp.gridcell"}, {"fields": {}, "pk": "B13", "model": "fileApp.gridcell"}, {"fields": {}, "pk": "B14", "model": "fileApp.gridcell"}, {"fields": {}, "pk": "B15", "model": "fileApp.gridcell"}, {"fields": {}, "pk": "B16", "model": "fileApp.gridcell"}, {"fields": {}, "pk": "B17", "model": "fileApp.gridcell"}, {"fields": {}, "pk": "B18", "model": "fileApp.gridcell"}, {"fields": {}, "pk": "B19", "model": "fileApp.gridcell"}, {"fields": {}, "pk": "B20", "model": "fileApp.gridcell"}, {"fields": {}, "pk": "B21", "model": "fileApp.gridcell"}, {"fields": {}, "pk": "B22", "model": "fileApp.gridcell"}, {"fields": {}, "pk": "B23", "model": "fileApp.gridcell"}, {"fields": {}, "pk": "B24", "model": "fileApp.gridcell"}, {"fields": {}, "pk": "B25", "model": "fileApp.gridcell"}, {"fields": {}, "pk": "B26", "model": "fileApp.gridcell"}, {"fields": {}, "pk": "B27", "model": "fileApp.gridcell"}, {"fields": {}, "pk": "B28", "model": "fileApp.gridcell"}, {"fields": {}, "pk": "B29", "model": "fileApp.gridcell"}, {"fields": {}, "pk": "B30", "model": "fileApp.gridcell"}, {"fields": {}, "pk": "B31", "model": "fileApp.gridcell"}, {"fields": {}, "pk": "B32", "model": "fileApp.gridcell"}, {"fields": {}, "pk": "B33", "model": "fileApp.gridcell"}, {"fields": {}, "pk": "B34", "model": "fileApp.gridcell"}, {"fields": {}, "pk": "B35", "model": "fileApp.gridcell"}, {"fields": {}, "pk": "B36", "model": "fileApp.gridcell"}, {"fields": {}, "pk": "B37", "model": "fileApp.gridcell"}, {"fields": {}, "pk": "B38", "model": "fileApp.gridcell"}, {"fields": {}, "pk": "B39", "model": "fileApp.gridcell"}, {"fields": {}, "pk": "B40", "model": "fileApp.gridcell"}, {"fields": {}, "pk": "B41", "model": "fileApp.gridcell"}, {"fields": {}, "pk": "B42", "model": "fileApp.gridcell"}, {"fields": {}, "pk": "B43", "model": "fileApp.gridcell"}, {"fields": {}, "pk": "B44", "model": "fileApp.gridcell"}, {"fields": {}, "pk": "C01", "model": "fileApp.gridcell"}, {"fields": {}, "pk": "C02", "model": "fileApp.gridcell"}, {"fields": {}, "pk": "C03", "model": "fileApp.gridcell"}, {"fields": {}, "pk": "C04", "model": "fileApp.gridcell"}, {"fields": {}, "pk": "C05", "model": "fileApp.gridcell"}, {"fields": {}, "pk": "C06", "model": "fileApp.gridcell"}, {"fields": {}, "pk": "C07", "model": "fileApp.gridcell"}, {"fields": {}, "pk": "C08", "model": "fileApp.gridcell"}, {"fields": {}, "pk": "C09", "model": "fileApp.gridcell"}, {"fields": {}, "pk": "C10", "model": "fileApp.gridcell"}, {"fields": {}, "pk": "C11", "model": "fileApp.gridcell"}, {"fields": {}, "pk": "C12", "model": "fileApp.gridcell"}, {"fields": {}, "pk": "C13", "model": "fileApp.gridcell"}, {"fields": {}, "pk": "C14", "model": "fileApp.gridcell"}, {"fields": {}, "pk": "C15", "model": "fileApp.gridcell"}, {"fields": {}, "pk": "C16", "model": "fileApp.gridcell"}, {"fields": {}, "pk": "C17", "model": "fileApp.gridcell"}, {"fields": {}, "pk": "C18", "model": "fileApp.gridcell"}, {"fields": {}, "pk": "C19", "model": "fileApp.gridcell"}, {"fields": {}, "pk": "C20", "model": "fileApp.gridcell"}, {"fields": {}, "pk": "C21", "model": "fileApp.gridcell"}, {"fields": {}, "pk": "C22", "model": "fileApp.gridcell"}, {"fields": {}, "pk": "C23", "model": "fileApp.gridcell"}, {"fields": {}, "pk": "C24", "model": "fileApp.gridcell"}, {"fields": {}, "pk": "C25", "model": "fileApp.gridcell"}, {"fields": {}, "pk": "C26", "model": "fileApp.gridcell"}, {"fields": {}, "pk": "C27", "model": "fileApp.gridcell"}, {"fields": {}, "pk": "C28", "model": "fileApp.gridcell"}, {"fields": {}, "pk": "C29", "model": "fileApp.gridcell"}, {"fields": {}, "pk": "C30", "model": "fileApp.gridcell"}, {"fields": {}, "pk": "C31", "model": "fileApp.gridcell"}, {"fields": {}, "pk": "C32", "model": "fileApp.gridcell"}, {"fields": {}, "pk": "C33", "model": "fileApp.gridcell"}, {"fields": {}, "pk": "C34", "model": "fileApp.gridcell"}, {"fields": {}, "pk": "C35", "model": "fileApp.gridcell"}, {"fields": {}, "pk": "C36", "model": "fileApp.gridcell"}, {"fields": {}, "pk": "C37", "model": "fileApp.gridcell"}, {"fields": {}, "pk": "C38", "model": "fileApp.gridcell"}, {"fields": {}, "pk": "C39", "model": "fileApp.gridcell"}, {"fields": {}, "pk": "C40", "model": "fileApp.gridcell"}, {"fields": {}, "pk": "C41", "model": "fileApp.gridcell"}, {"fields": {}, "pk": "C42", "model": "fileApp.gridcell"}, {"fields": {}, "pk": "C43", "model": "fileApp.gridcell"}, {"fields": {}, "pk": "C44", "model": "fileApp.gridcell"}, {"fields": {}, "pk": "D01", "model": "fileApp.gridcell"}, {"fields": {}, "pk": "D02", "model": "fileApp.gridcell"}, {"fields": {}, "pk": "D03", "model": "fileApp.gridcell"}, {"fields": {}, "pk": "D04", "model": "fileApp.gridcell"}, {"fields": {}, "pk": "D05", "model": "fileApp.gridcell"}, {"fields": {}, "pk": "D06", "model": "fileApp.gridcell"}, {"fields": {}, "pk": "D07", "model": "fileApp.gridcell"}, {"fields": {}, "pk": "D08", "model": "fileApp.gridcell"}, {"fields": {}, "pk": "D09", "model": "fileApp.gridcell"}, {"fields": {}, "pk": "D10", "model": "fileApp.gridcell"}, {"fields": {}, "pk": "D11", "model": "fileApp.gridcell"}, {"fields": {}, "pk": "D12", "model": "fileApp.gridcell"}, {"fields": {}, "pk": "D13", "model": "fileApp.gridcell"}, {"fields": {}, "pk": "D14", "model": "fileApp.gridcell"}, {"fields": {}, "pk": "D15", "model": "fileApp.gridcell"}, {"fields": {}, "pk": "D16", "model": "fileApp.gridcell"}, {"fields": {}, "pk": "D17", "model": "fileApp.gridcell"}, {"fields": {}, "pk": "D18", "model": "fileApp.gridcell"}, {"fields": {}, "pk": "D19", "model": "fileApp.gridcell"}, {"fields": {}, "pk": "D20", "model": "fileApp.gridcell"}, {"fields": {}, "pk": "D21", "model": "fileApp.gridcell"}, {"fields": {}, "pk": "D22", "model": "fileApp.gridcell"}, {"fields": {}, "pk": "D23", "model": "fileApp.gridcell"}, {"fields": {}, "pk": "D24", "model": "fileApp.gridcell"}, {"fields": {}, "pk": "D25", "model": "fileApp.gridcell"}, {"fields": {}, "pk": "D26", "model": "fileApp.gridcell"}, {"fields": {}, "pk": "D27", "model": "fileApp.gridcell"}, {"fields": {}, "pk": "D28", "model": "fileApp.gridcell"}, {"fields": {}, "pk": "D29", "model": "fileApp.gridcell"}, {"fields": {}, "pk": "D30", "model": "fileApp.gridcell"}, {"fields": {}, "pk": "D31", "model": "fileApp.gridcell"}, {"fields": {}, "pk": "D32", "model": "fileApp.gridcell"}, {"fields": {}, "pk": "D33", "model": "fileApp.gridcell"}, {"fields": {}, "pk": "D34", "model": "fileApp.gridcell"}, {"fields": {}, "pk": "D35", "model": "fileApp.gridcell"}, {"fields": {}, "pk": "D36", "model": "fileApp.gridcell"}, {"fields": {}, "pk": "D37", "model": "fileApp.gridcell"}, {"fields": {}, "pk": "D38", "model": "fileApp.gridcell"}, {"fields": {}, "pk": "D39", "model": "fileApp.gridcell"}, {"fields": {}, "pk": "D40", "model": "fileApp.gridcell"}, {"fields": {}, "pk": "D41", "model": "fileApp.gridcell"}, {"fields": {}, "pk": "D42", "model": "fileApp.gridcell"}, {"fields": {}, "pk": "D43", "model": "fileApp.gridcell"}, {"fields": {}, "pk": "D44", "model": "fileApp.gridcell"}, {"fields": {}, "pk": "E01", "model": "fileApp.gridcell"}, {"fields": {}, "pk": "E02", "model": "fileApp.gridcell"}, {"fields": {}, "pk": "E03", "model": "fileApp.gridcell"}, {"fields": {}, "pk": "E04", "model": "fileApp.gridcell"}, {"fields": {}, "pk": "E05", "model": "fileApp.gridcell"}, {"fields": {}, "pk": "E06", "model": "fileApp.gridcell"}, {"fields": {}, "pk": "E07", "model": "fileApp.gridcell"}, {"fields": {}, "pk": "E08", "model": "fileApp.gridcell"}, {"fields": {}, "pk": "E09", "model": "fileApp.gridcell"}, {"fields": {}, "pk": "E10", "model": "fileApp.gridcell"}, {"fields": {}, "pk": "E11", "model": "fileApp.gridcell"}, {"fields": {}, "pk": "E12", "model": "fileApp.gridcell"}, {"fields": {}, "pk": "E13", "model": "fileApp.gridcell"}, {"fields": {}, "pk": "E14", "model": "fileApp.gridcell"}, {"fields": {}, "pk": "E15", "model": "fileApp.gridcell"}, {"fields": {}, "pk": "E16", "model": "fileApp.gridcell"}, {"fields": {}, "pk": "E17", "model": "fileApp.gridcell"}, {"fields": {}, "pk": "E18", "model": "fileApp.gridcell"}, {"fields": {}, "pk": "E19", "model": "fileApp.gridcell"}, {"fields": {}, "pk": "E20", "model": "fileApp.gridcell"}, {"fields": {}, "pk": "E21", "model": "fileApp.gridcell"}, {"fields": {}, "pk": "E22", "model": "fileApp.gridcell"}, {"fields": {}, "pk": "E23", "model": "fileApp.gridcell"}, {"fields": {}, "pk": "E24", "model": "fileApp.gridcell"}, {"fields": {}, "pk": "E25", "model": "fileApp.gridcell"}, {"fields": {}, "pk": "E26", "model": "fileApp.gridcell"}, {"fields": {}, "pk": "E27", "model": "fileApp.gridcell"}, {"fields": {}, "pk": "E28", "model": "fileApp.gridcell"}, {"fields": {}, "pk": "E29", "model": "fileApp.gridcell"}, {"fields": {}, "pk": "E30", "model": "fileApp.gridcell"}, {"fields": {}, "pk": "E31", "model": "fileApp.gridcell"}, {"fields": {}, "pk": "E32", "model": "fileApp.gridcell"}, {"fields": {}, "pk": "E33", "model": "fileApp.gridcell"}, {"fields": {}, "pk": "E34", "model": "fileApp.gridcell"}, {"fields": {}, "pk": "E35", "model": "fileApp.gridcell"}, {"fields": {}, "pk": "E36", "model": "fileApp.gridcell"}, {"fields": {}, "pk": "E37", "model": "fileApp.gridcell"}, {"fields": {}, "pk": "E38", "model": "fileApp.gridcell"}, {"fields": {}, "pk": "E39", "model": "fileApp.gridcell"}, {"fields": {}, "pk": "E40", "model": "fileApp.gridcell"}, {"fields": {}, "pk": "E41", "model": "fileApp.gridcell"}, {"fields": {}, "pk": "E42", "model": "fileApp.gridcell"}, {"fields": {}, "pk": "E43", "model": "fileApp.gridcell"}, {"fields": {}, "pk": "E44", "model": "fileApp.gridcell"}, {"fields": {}, "pk": "F01", "model": "fileApp.gridcell"}, {"fields": {}, "pk": "F02", "model": "fileApp.gridcell"}, {"fields": {}, "pk": "F03", "model": "fileApp.gridcell"}, {"fields": {}, "pk": "F04", "model": "fileApp.gridcell"}, {"fields": {}, "pk": "F05", "model": "fileApp.gridcell"}, {"fields": {}, "pk": "F06", "model": "fileApp.gridcell"}, {"fields": {}, "pk": "F07", "model": "fileApp.gridcell"}, {"fields": {}, "pk": "F08", "model": "fileApp.gridcell"}, {"fields": {}, "pk": "F09", "model": "fileApp.gridcell"}, {"fields": {}, "pk": "F10", "model": "fileApp.gridcell"}, {"fields": {}, "pk": "F11", "model": "fileApp.gridcell"}, {"fields": {}, "pk": "F12", "model": "fileApp.gridcell"}, {"fields": {}, "pk": "F13", "model": "fileApp.gridcell"}, {"fields": {}, "pk": "F14", "model": "fileApp.gridcell"}, {"fields": {}, "pk": "F15", "model": "fileApp.gridcell"}, {"fields": {}, "pk": "F16", "model": "fileApp.gridcell"}, {"fields": {}, "pk": "F17", "model": "fileApp.gridcell"}, {"fields": {}, "pk": "F18", "model": "fileApp.gridcell"}, {"fields": {}, "pk": "F19", "model": "fileApp.gridcell"}, {"fields": {}, "pk": "F20", "model": "fileApp.gridcell"}, {"fields": {}, "pk": "F21", "model": "fileApp.gridcell"}, {"fields": {}, "pk": "F22", "model": "fileApp.gridcell"}, {"fields": {}, "pk": "F23", "model": "fileApp.gridcell"}, {"fields": {}, "pk": "F24", "model": "fileApp.gridcell"}, {"fields": {}, "pk": "F25", "model": "fileApp.gridcell"}, {"fields": {}, "pk": "F26", "model": "fileApp.gridcell"}, {"fields": {}, "pk": "F27", "model": "fileApp.gridcell"}, {"fields": {}, "pk": "F28", "model": "fileApp.gridcell"}, {"fields": {}, "pk": "F29", "model": "fileApp.gridcell"}, {"fields": {}, "pk": "F30", "model": "fileApp.gridcell"}, {"fields": {}, "pk": "F31", "model": "fileApp.gridcell"}, {"fields": {}, "pk": "F32", "model": "fileApp.gridcell"}, {"fields": {}, "pk": "F33", "model": "fileApp.gridcell"}, {"fields": {}, "pk": "F34", "model": "fileApp.gridcell"}, {"fields": {}, "pk": "F35", "model": "fileApp.gridcell"}, {"fields": {}, "pk": "F36", "model": "fileApp.gridcell"}, {"fields": {}, "pk": "F37", "model": "fileApp.gridcell"}, {"fields": {}, "pk": "F38", "model": "fileApp.gridcell"}, {"fields": {}, "pk": "F39", "model": "fileApp.gridcell"}, {"fields": {}, "pk": "F40", "model": "fileApp.gridcell"}, {"fields": {}, "pk": "F41", "model": "fileApp.gridcell"}, {"fields": {}, "pk": "F42", "model": "fileApp.gridcell"}, {"fields": {}, "pk": "F43", "model": "fileApp.gridcell"}, {"fields": {}, "pk": "F44", "model": "fileApp.gridcell"}, {"fields": {}, "pk": "G01", "model": "fileApp.gridcell"}, {"fields": {}, "pk": "G02", "model": "fileApp.gridcell"}, {"fields": {}, "pk": "G03", "model": "fileApp.gridcell"}, {"fields": {}, "pk": "G04", "model": "fileApp.gridcell"}, {"fields": {}, "pk": "G05", "model": "fileApp.gridcell"}, {"fields": {}, "pk": "G06", "model": "fileApp.gridcell"}, {"fields": {}, "pk": "G07", "model": "fileApp.gridcell"}, {"fields": {}, "pk": "G08", "model": "fileApp.gridcell"}, {"fields": {}, "pk": "G09", "model": "fileApp.gridcell"}, {"fields": {}, "pk": "G10", "model": "fileApp.gridcell"}, {"fields": {}, "pk": "G11", "model": "fileApp.gridcell"}, {"fields": {}, "pk": "G12", "model": "fileApp.gridcell"}, {"fields": {}, "pk": "G13", "model": "fileApp.gridcell"}, {"fields": {}, "pk": "G14", "model": "fileApp.gridcell"}, {"fields": {}, "pk": "G15", "model": "fileApp.gridcell"}, {"fields": {}, "pk": "G16", "model": "fileApp.gridcell"}, {"fields": {}, "pk": "G17", "model": "fileApp.gridcell"}, {"fields": {}, "pk": "G18", "model": "fileApp.gridcell"}, {"fields": {}, "pk": "G19", "model": "fileApp.gridcell"}, {"fields": {}, "pk": "G20", "model": "fileApp.gridcell"}, {"fields": {}, "pk": "G21", "model": "fileApp.gridcell"}, {"fields": {}, "pk": "G22", "model": "fileApp.gridcell"}, {"fields": {}, "pk": "G23", "model": "fileApp.gridcell"}, {"fields": {}, "pk": "G24", "model": "fileApp.gridcell"}, {"fields": {}, "pk": "G25", "model": "fileApp.gridcell"}, {"fields": {}, "pk": "G26", "model": "fileApp.gridcell"}, {"fields": {}, "pk": "G27", "model": "fileApp.gridcell"}, {"fields": {}, "pk": "G28", "model": "fileApp.gridcell"}, {"fields": {}, "pk": "G29", "model": "fileApp.gridcell"}, {"fields": {}, "pk": "G30", "model": "fileApp.gridcell"}, {"fields": {}, "pk": "G31", "model": "fileApp.gridcell"}, {"fields": {}, "pk": "G32", "model": "fileApp.gridcell"}, {"fields": {}, "pk": "G33", "model": "fileApp.gridcell"}, {"fields": {}, "pk": "G34", "model": "fileApp.gridcell"}, {"fields": {}, "pk": "G35", "model": "fileApp.gridcell"}, {"fields": {}, "pk": "G36", "model": "fileApp.gridcell"}, {"fields": {}, "pk": "G37", "model": "fileApp.gridcell"}, {"fields": {}, "pk": "G38", "model": "fileApp.gridcell"}, {"fields": {}, "pk": "G39", "model": "fileApp.gridcell"}, {"fields": {}, "pk": "G40", "model": "fileApp.gridcell"}, {"fields": {}, "pk": "G41", "model": "fileApp.gridcell"}, {"fields": {}, "pk": "G42", "model": "fileApp.gridcell"}, {"fields": {}, "pk": "G43", "model": "fileApp.gridcell"}, {"fields": {}, "pk": "G44", "model": "fileApp.gridcell"}, {"fields": {}, "pk": "H01", "model": "fileApp.gridcell"}, {"fields": {}, "pk": "H02", "model": "fileApp.gridcell"}, {"fields": {}, "pk": "H03", "model": "fileApp.gridcell"}, {"fields": {}, "pk": "H04", "model": "fileApp.gridcell"}, {"fields": {}, "pk": "H05", "model": "fileApp.gridcell"}, {"fields": {}, "pk": "H06", "model": "fileApp.gridcell"}, {"fields": {}, "pk": "H07", "model": "fileApp.gridcell"}, {"fields": {}, "pk": "H08", "model": "fileApp.gridcell"}, {"fields": {}, "pk": "H09", "model": "fileApp.gridcell"}, {"fields": {}, "pk": "H10", "model": "fileApp.gridcell"}, {"fields": {}, "pk": "H11", "model": "fileApp.gridcell"}, {"fields": {}, "pk": "H12", "model": "fileApp.gridcell"}, {"fields": {}, "pk": "H13", "model": "fileApp.gridcell"}, {"fields": {}, "pk": "H14", "model": "fileApp.gridcell"}, {"fields": {}, "pk": "H15", "model": "fileApp.gridcell"}, {"fields": {}, "pk": "H16", "model": "fileApp.gridcell"}, {"fields": {}, "pk": "H17", "model": "fileApp.gridcell"}, {"fields": {}, "pk": "H18", "model": "fileApp.gridcell"}, {"fields": {}, "pk": "H19", "model": "fileApp.gridcell"}, {"fields": {}, "pk": "H20", "model": "fileApp.gridcell"}, {"fields": {}, "pk": "H21", "model": "fileApp.gridcell"}, {"fields": {}, "pk": "H22", "model": "fileApp.gridcell"}, {"fields": {}, "pk": "H23", "model": "fileApp.gridcell"}, {"fields": {}, "pk": "H24", "model": "fileApp.gridcell"}, {"fields": {}, "pk": "H25", "model": "fileApp.gridcell"}, {"fields": {}, "pk": "H26", "model": "fileApp.gridcell"}, {"fields": {}, "pk": "H27", "model": "fileApp.gridcell"}, {"fields": {}, "pk": "H28", "model": "fileApp.gridcell"}, {"fields": {}, "pk": "H29", "model": "fileApp.gridcell"}, {"fields": {}, "pk": "H30", "model": "fileApp.gridcell"}, {"fields": {}, "pk": "H31", "model": "fileApp.gridcell"}, {"fields": {}, "pk": "H32", "model": "fileApp.gridcell"}, {"fields": {}, "pk": "H33", "model": "fileApp.gridcell"}, {"fields": {}, "pk": "H34", "model": "fileApp.gridcell"}, {"fields": {}, "pk": "H35", "model": "fileApp.gridcell"}, {"fields": {}, "pk": "H36", "model": "fileApp.gridcell"}, {"fields": {}, "pk": "H37", "model": "fileApp.gridcell"}, {"fields": {}, "pk": "H38", "model": "fileApp.gridcell"}, {"fields": {}, "pk": "H39", "model": "fileApp.gridcell"}, {"fields": {}, "pk": "H40", "model": "fileApp.gridcell"}, {"fields": {}, "pk": "H41", "model": "fileApp.gridcell"}, {"fields": {}, "pk": "H42", "model": "fileApp.gridcell"}, {"fields": {}, "pk": "H43", "model": "fileApp.gridcell"}, {"fields": {}, "pk": "H44", "model": "fileApp.gridcell"}, {"fields": {}, "pk": "J01", "model": "fileApp.gridcell"}, {"fields": {}, "pk": "J02", "model": "fileApp.gridcell"}, {"fields": {}, "pk": "J03", "model": "fileApp.gridcell"}, {"fields": {}, "pk": "J04", "model": "fileApp.gridcell"}, {"fields": {}, "pk": "J05", "model": "fileApp.gridcell"}, {"fields": {}, "pk": "J06", "model": "fileApp.gridcell"}, {"fields": {}, "pk": "J07", "model": "fileApp.gridcell"}, {"fields": {}, "pk": "J08", "model": "fileApp.gridcell"}, {"fields": {}, "pk": "J09", "model": "fileApp.gridcell"}, {"fields": {}, "pk": "J10", "model": "fileApp.gridcell"}, {"fields": {}, "pk": "J11", "model": "fileApp.gridcell"}, {"fields": {}, "pk": "J12", "model": "fileApp.gridcell"}, {"fields": {}, "pk": "J13", "model": "fileApp.gridcell"}, {"fields": {}, "pk": "J14", "model": "fileApp.gridcell"}, {"fields": {}, "pk": "J15", "model": "fileApp.gridcell"}, {"fields": {}, "pk": "J16", "model": "fileApp.gridcell"}, {"fields": {}, "pk": "J17", "model": "fileApp.gridcell"}, {"fields": {}, "pk": "J18", "model": "fileApp.gridcell"}, {"fields": {}, "pk": "J19", "model": "fileApp.gridcell"}, {"fields": {}, "pk": "J20", "model": "fileApp.gridcell"}, {"fields": {}, "pk": "J21", "model": "fileApp.gridcell"}, {"fields": {}, "pk": "J22", "model": "fileApp.gridcell"}, {"fields": {}, "pk": "J23", "model": "fileApp.gridcell"}, {"fields": {}, "pk": "J24", "model": "fileApp.gridcell"}, {"fields": {}, "pk": "J25", "model": "fileApp.gridcell"}, {"fields": {}, "pk": "J26", "model": "fileApp.gridcell"}, {"fields": {}, "pk": "J27", "model": "fileApp.gridcell"}, {"fields": {}, "pk": "J28", "model": "fileApp.gridcell"}, {"fields": {}, "pk": "J29", "model": "fileApp.gridcell"}, {"fields": {}, "pk": "J30", "model": "fileApp.gridcell"}, {"fields": {}, "pk": "J31", "model": "fileApp.gridcell"}, {"fields": {}, "pk": "J32", "model": "fileApp.gridcell"}, {"fields": {}, "pk": "J33", "model": "fileApp.gridcell"}, {"fields": {}, "pk": "J34", "model": "fileApp.gridcell"}, {"fields": {}, "pk": "J35", "model": "fileApp.gridcell"}, {"fields": {}, "pk": "J36", "model": "fileApp.gridcell"}, {"fields": {}, "pk": "J37", "model": "fileApp.gridcell"}, {"fields": {}, "pk": "J38", "model": "fileApp.gridcell"}, {"fields": {}, "pk": "J39", "model": "fileApp.gridcell"}, {"fields": {}, "pk": "J40", "model": "fileApp.gridcell"}, {"fields": {}, "pk": "J41", "model": "fileApp.gridcell"}, {"fields": {}, "pk": "J42", "model": "fileApp.gridcell"}, {"fields": {}, "pk": "J43", "model": "fileApp.gridcell"}, {"fields": {}, "pk": "J44", "model": "fileApp.gridcell"}, {"fields": {}, "pk": "K01", "model": "fileApp.gridcell"}, {"fields": {}, "pk": "K02", "model": "fileApp.gridcell"}, {"fields": {}, "pk": "K03", "model": "fileApp.gridcell"}, {"fields": {}, "pk": "K04", "model": "fileApp.gridcell"}, {"fields": {}, "pk": "K05", "model": "fileApp.gridcell"}, {"fields": {}, "pk": "K06", "model": "fileApp.gridcell"}, {"fields": {}, "pk": "K07", "model": "fileApp.gridcell"}, {"fields": {}, "pk": "K08", "model": "fileApp.gridcell"}, {"fields": {}, "pk": "K09", "model": "fileApp.gridcell"}, {"fields": {}, "pk": "K10", "model": "fileApp.gridcell"}, {"fields": {}, "pk": "K11", "model": "fileApp.gridcell"}, {"fields": {}, "pk": "K12", "model": "fileApp.gridcell"}, {"fields": {}, "pk": "K13", "model": "fileApp.gridcell"}, {"fields": {}, "pk": "K14", "model": "fileApp.gridcell"}, {"fields": {}, "pk": "K15", "model": "fileApp.gridcell"}, {"fields": {}, "pk": "K16", "model": "fileApp.gridcell"}, {"fields": {}, "pk": "K17", "model": "fileApp.gridcell"}, {"fields": {}, "pk": "K18", "model": "fileApp.gridcell"}, {"fields": {}, "pk": "K19", "model": "fileApp.gridcell"}, {"fields": {}, "pk": "K20", "model": "fileApp.gridcell"}, {"fields": {}, "pk": "K21", "model": "fileApp.gridcell"}, {"fields": {}, "pk": "K22", "model": "fileApp.gridcell"}, {"fields": {}, "pk": "K23", "model": "fileApp.gridcell"}, {"fields": {}, "pk": "K24", "model": "fileApp.gridcell"}, {"fields": {}, "pk": "K25", "model": "fileApp.gridcell"}, {"fields": {}, "pk": "K26", "model": "fileApp.gridcell"}, {"fields": {}, "pk": "K27", "model": "fileApp.gridcell"}, {"fields": {}, "pk": "K28", "model": "fileApp.gridcell"}, {"fields": {}, "pk": "K29", "model": "fileApp.gridcell"}, {"fields": {}, "pk": "K30", "model": "fileApp.gridcell"}, {"fields": {}, "pk": "K31", "model": "fileApp.gridcell"}, {"fields": {}, "pk": "K32", "model": "fileApp.gridcell"}, {"fields": {}, "pk": "K33", "model": "fileApp.gridcell"}, {"fields": {}, "pk": "K34", "model": "fileApp.gridcell"}, {"fields": {}, "pk": "K35", "model": "fileApp.gridcell"}, {"fields": {}, "pk": "K36", "model": "fileApp.gridcell"}, {"fields": {}, "pk": "K37", "model": "fileApp.gridcell"}, {"fields": {}, "pk": "K38", "model": "fileApp.gridcell"}, {"fields": {}, "pk": "K39", "model": "fileApp.gridcell"}, {"fields": {}, "pk": "K40", "model": "fileApp.gridcell"}, {"fields": {}, "pk": "K41", "model": "fileApp.gridcell"}, {"fields": {}, "pk": "K42", "model": "fileApp.gridcell"}, {"fields": {}, "pk": "K43", "model": "fileApp.gridcell"}, {"fields": {}, "pk": "K44", "model": "fileApp.gridcell"}, {"fields": {}, "pk": "L01", "model": "fileApp.gridcell"}, {"fields": {}, "pk": "L02", "model": "fileApp.gridcell"}, {"fields": {}, "pk": "L03", "model": "fileApp.gridcell"}, {"fields": {}, "pk": "L04", "model": "fileApp.gridcell"}, {"fields": {}, "pk": "L05", "model": "fileApp.gridcell"}, {"fields": {}, "pk": "L06", "model": "fileApp.gridcell"}, {"fields": {}, "pk": "L07", "model": "fileApp.gridcell"}, {"fields": {}, "pk": "L08", "model": "fileApp.gridcell"}, {"fields": {}, "pk": "L09", "model": "fileApp.gridcell"}, {"fields": {}, "pk": "L10", "model": "fileApp.gridcell"}, {"fields": {}, "pk": "L11", "model": "fileApp.gridcell"}, {"fields": {}, "pk": "L12", "model": "fileApp.gridcell"}, {"fields": {}, "pk": "L13", "model": "fileApp.gridcell"}, {"fields": {}, "pk": "L14", "model": "fileApp.gridcell"}, {"fields": {}, "pk": "L15", "model": "fileApp.gridcell"}, {"fields": {}, "pk": "L16", "model": "fileApp.gridcell"}, {"fields": {}, "pk": "L17", "model": "fileApp.gridcell"}, {"fields": {}, "pk": "L18", "model": "fileApp.gridcell"}, {"fields": {}, "pk": "L19", "model": "fileApp.gridcell"}, {"fields": {}, "pk": "L20", "model": "fileApp.gridcell"}, {"fields": {}, "pk": "L21", "model": "fileApp.gridcell"}, {"fields": {}, "pk": "L22", "model": "fileApp.gridcell"}, {"fields": {}, "pk": "L23", "model": "fileApp.gridcell"}, {"fields": {}, "pk": "L24", "model": "fileApp.gridcell"}, {"fields": {}, "pk": "L25", "model": "fileApp.gridcell"}, {"fields": {}, "pk": "L26", "model": "fileApp.gridcell"}, {"fields": {}, "pk": "L27", "model": "fileApp.gridcell"}, {"fields": {}, "pk": "L28", "model": "fileApp.gridcell"}, {"fields": {}, "pk": "L29", "model": "fileApp.gridcell"}, {"fields": {}, "pk": "L30", "model": "fileApp.gridcell"}, {"fields": {}, "pk": "L31", "model": "fileApp.gridcell"}, {"fields": {}, "pk": "L32", "model": "fileApp.gridcell"}, {"fields": {}, "pk": "L33", "model": "fileApp.gridcell"}, {"fields": {}, "pk": "L34", "model": "fileApp.gridcell"}, {"fields": {}, "pk": "L36", "model": "fileApp.gridcell"}, {"fields": {}, "pk": "L37", "model": "fileApp.gridcell"}, {"fields": {}, "pk": "L38", "model": "fileApp.gridcell"}, {"fields": {}, "pk": "L39", "model": "fileApp.gridcell"}, {"fields": {}, "pk": "L40", "model": "fileApp.gridcell"}, {"fields": {}, "pk": "L41", "model": "fileApp.gridcell"}, {"fields": {}, "pk": "L42", "model": "fileApp.gridcell"}, {"fields": {}, "pk": "L43", "model": "fileApp.gridcell"}, {"fields": {}, "pk": "L44", "model": "fileApp.gridcell"}, {"fields": {}, "pk": "M01", "model": "fileApp.gridcell"}, {"fields": {}, "pk": "M02", "model": "fileApp.gridcell"}, {"fields": {}, "pk": "M03", "model": "fileApp.gridcell"}, {"fields": {}, "pk": "M04", "model": "fileApp.gridcell"}, {"fields": {}, "pk": "M05", "model": "fileApp.gridcell"}, {"fields": {}, "pk": "M06", "model": "fileApp.gridcell"}, {"fields": {}, "pk": "M07", "model": "fileApp.gridcell"}, {"fields": {}, "pk": "M08", "model": "fileApp.gridcell"}, {"fields": {}, "pk": "M09", "model": "fileApp.gridcell"}, {"fields": {}, "pk": "M10", "model": "fileApp.gridcell"}, {"fields": {}, "pk": "M11", "model": "fileApp.gridcell"}, {"fields": {}, "pk": "M12", "model": "fileApp.gridcell"}, {"fields": {}, "pk": "M13", "model": "fileApp.gridcell"}, {"fields": {}, "pk": "M14", "model": "fileApp.gridcell"}, {"fields": {}, "pk": "M15", "model": "fileApp.gridcell"}, {"fields": {}, "pk": "M16", "model": "fileApp.gridcell"}, {"fields": {}, "pk": "M17", "model": "fileApp.gridcell"}, {"fields": {}, "pk": "M18", "model": "fileApp.gridcell"}, {"fields": {}, "pk": "M19", "model": "fileApp.gridcell"}, {"fields": {}, "pk": "M20", "model": "fileApp.gridcell"}, {"fields": {}, "pk": "M21", "model": "fileApp.gridcell"}, {"fields": {}, "pk": "M22", "model": "fileApp.gridcell"}, {"fields": {}, "pk": "M23", "model": "fileApp.gridcell"}, {"fields": {}, "pk": "M25", "model": "fileApp.gridcell"}, {"fields": {}, "pk": "M26", "model": "fileApp.gridcell"}, {"fields": {}, "pk": "M27", "model": "fileApp.gridcell"}, {"fields": {}, "pk": "M28", "model": "fileApp.gridcell"}, {"fields": {}, "pk": "M29", "model": "fileApp.gridcell"}, {"fields": {}, "pk": "M30", "model": "fileApp.gridcell"}, {"fields": {}, "pk": "M31", "model": "fileApp.gridcell"}, {"fields": {}, "pk": "M32", "model": "fileApp.gridcell"}, {"fields": {}, "pk": "M33", "model": "fileApp.gridcell"}, {"fields": {}, "pk": "M34", "model": "fileApp.gridcell"}, {"fields": {}, "pk": "M35", "model": "fileApp.gridcell"}, {"fields": {}, "pk": "M36", "model": "fileApp.gridcell"}, {"fields": {}, "pk": "M37", "model": "fileApp.gridcell"}, {"fields": {}, "pk": "M38", "model": "fileApp.gridcell"}, {"fields": {}, "pk": "M39", "model": "fileApp.gridcell"}, {"fields": {}, "pk": "M40", "model": "fileApp.gridcell"}, {"fields": {}, "pk": "M41", "model": "fileApp.gridcell"}, {"fields": {}, "pk": "M42", "model": "fileApp.gridcell"}, {"fields": {}, "pk": "M43", "model": "fileApp.gridcell"}, {"fields": {}, "pk": "M44", "model": "fileApp.gridcell"}, {"fields": {}, "pk": "N01", "model": "fileApp.gridcell"}, {"fields": {}, "pk": "N02", "model": "fileApp.gridcell"}, {"fields": {}, "pk": "N03", "model": "fileApp.gridcell"}, {"fields": {}, "pk": "N04", "model": "fileApp.gridcell"}, {"fields": {}, "pk": "N05", "model": "fileApp.gridcell"}, {"fields": {}, "pk": "N06", "model": "fileApp.gridcell"}, {"fields": {}, "pk": "N07", "model": "fileApp.gridcell"}, {"fields": {}, "pk": "N08", "model": "fileApp.gridcell"}, {"fields": {}, "pk": "N09", "model": "fileApp.gridcell"}, {"fields": {}, "pk": "N10", "model": "fileApp.gridcell"}, {"fields": {}, "pk": "N11", "model": "fileApp.gridcell"}, {"fields": {}, "pk": "N12", "model": "fileApp.gridcell"}, {"fields": {}, "pk": "N13", "model": "fileApp.gridcell"}, {"fields": {}, "pk": "N14", "model": "fileApp.gridcell"}, {"fields": {}, "pk": "N15", "model": "fileApp.gridcell"}, {"fields": {}, "pk": "N16", "model": "fileApp.gridcell"}, {"fields": {}, "pk": "N17", "model": "fileApp.gridcell"}, {"fields": {}, "pk": "N18", "model": "fileApp.gridcell"}, {"fields": {}, "pk": "N19", "model": "fileApp.gridcell"}, {"fields": {}, "pk": "N20", "model": "fileApp.gridcell"}, {"fields": {}, "pk": "N21", "model": "fileApp.gridcell"}, {"fields": {}, "pk": "N22", "model": "fileApp.gridcell"}, {"fields": {}, "pk": "N23", "model": "fileApp.gridcell"}, {"fields": {}, "pk": "N24", "model": "fileApp.gridcell"}, {"fields": {}, "pk": "N25", "model": "fileApp.gridcell"}, {"fields": {}, "pk": "N26", "model": "fileApp.gridcell"}, {"fields": {}, "pk": "N27", "model": "fileApp.gridcell"}, {"fields": {}, "pk": "N28", "model": "fileApp.gridcell"}, {"fields": {}, "pk": "N29", "model": "fileApp.gridcell"}, {"fields": {}, "pk": "N30", "model": "fileApp.gridcell"}, {"fields": {}, "pk": "N31", "model": "fileApp.gridcell"}, {"fields": {}, "pk": "N32", "model": "fileApp.gridcell"}, {"fields": {}, "pk": "N33", "model": "fileApp.gridcell"}, {"fields": {}, "pk": "N34", "model": "fileApp.gridcell"}, {"fields": {}, "pk": "N35", "model": "fileApp.gridcell"}, {"fields": {}, "pk": "N36", "model": "fileApp.gridcell"}, {"fields": {}, "pk": "N37", "model": "fileApp.gridcell"}, {"fields": {}, "pk": "N38", "model": "fileApp.gridcell"}, {"fields": {}, "pk": "N39", "model": "fileApp.gridcell"}, {"fields": {}, "pk": "N40", "model": "fileApp.gridcell"}, {"fields": {}, "pk": "N41", "model": "fileApp.gridcell"}, {"fields": {}, "pk": "N42", "model": "fileApp.gridcell"}, {"fields": {}, "pk": "N43", "model": "fileApp.gridcell"}, {"fields": {}, "pk": "N44", "model": "fileApp.gridcell"}, {"fields": {}, "pk": "P01", "model": "fileApp.gridcell"}, {"fields": {}, "pk": "P02", "model": "fileApp.gridcell"}, {"fields": {}, "pk": "P03", "model": "fileApp.gridcell"}, {"fields": {}, "pk": "P04", "model": "fileApp.gridcell"}, {"fields": {}, "pk": "P05", "model": "fileApp.gridcell"}, {"fields": {}, "pk": "P06", "model": "fileApp.gridcell"}, {"fields": {}, "pk": "P07", "model": "fileApp.gridcell"}, {"fields": {}, "pk": "P08", "model": "fileApp.gridcell"}, {"fields": {}, "pk": "P09", "model": "fileApp.gridcell"}, {"fields": {}, "pk": "P10", "model": "fileApp.gridcell"}, {"fields": {}, "pk": "P11", "model": "fileApp.gridcell"}, {"fields": {}, "pk": "P12", "model": "fileApp.gridcell"}, {"fields": {}, "pk": "P13", "model": "fileApp.gridcell"}, {"fields": {}, "pk": "P14", "model": "fileApp.gridcell"}, {"fields": {}, "pk": "P15", "model": "fileApp.gridcell"}, {"fields": {}, "pk": "P16", "model": "fileApp.gridcell"}, {"fields": {}, "pk": "P17", "model": "fileApp.gridcell"}, {"fields": {}, "pk": "P18", "model": "fileApp.gridcell"}, {"fields": {}, "pk": "P19", "model": "fileApp.gridcell"}, {"fields": {}, "pk": "P20", "model": "fileApp.gridcell"}, {"fields": {}, "pk": "P21", "model": "fileApp.gridcell"}, {"fields": {}, "pk": "P22", "model": "fileApp.gridcell"}, {"fields": {}, "pk": "P23", "model": "fileApp.gridcell"}, {"fields": {}, "pk": "P24", "model": "fileApp.gridcell"}, {"fields": {}, "pk": "P25", "model": "fileApp.gridcell"}, {"fields": {}, "pk": "P26", "model": "fileApp.gridcell"}, {"fields": {}, "pk": "P27", "model": "fileApp.gridcell"}, {"fields": {}, "pk": "P28", "model": "fileApp.gridcell"}, {"fields": {}, "pk": "P29", "model": "fileApp.gridcell"}, {"fields": {}, "pk": "P30", "model": "fileApp.gridcell"}, {"fields": {}, "pk": "P31", "model": "fileApp.gridcell"}, {"fields": {}, "pk": "P32", "model": "fileApp.gridcell"}, {"fields": {}, "pk": "P33", "model": "fileApp.gridcell"}, {"fields": {}, "pk": "P34", "model": "fileApp.gridcell"}, {"fields": {}, "pk": "P35", "model": "fileApp.gridcell"}, {"fields": {}, "pk": "P36", "model": "fileApp.gridcell"}, {"fields": {}, "pk": "P37", "model": "fileApp.gridcell"}, {"fields": {}, "pk": "P38", "model": "fileApp.gridcell"}, {"fields": {}, "pk": "P39", "model": "fileApp.gridcell"}, {"fields": {}, "pk": "P40", "model": "fileApp.gridcell"}, {"fields": {}, "pk": "P41", "model": "fileApp.gridcell"}, {"fields": {}, "pk": "P42", "model": "fileApp.gridcell"}, {"fields": {}, "pk": "P43", "model": "fileApp.gridcell"}, {"fields": {}, "pk": "P44", "model": "fileApp.gridcell"}, {"fields": {}, "pk": "Q01", "model": "fileApp.gridcell"}, {"fields": {}, "pk": "Q02", "model": "fileApp.gridcell"}, {"fields": {}, "pk": "Q03", "model": "fileApp.gridcell"}, {"fields": {}, "pk": "Q04", "model": "fileApp.gridcell"}, {"fields": {}, "pk": "Q05", "model": "fileApp.gridcell"}, {"fields": {}, "pk": "Q06", "model": "fileApp.gridcell"}, {"fields": {}, "pk": "Q07", "model": "fileApp.gridcell"}, {"fields": {}, "pk": "Q08", "model": "fileApp.gridcell"}, {"fields": {}, "pk": "Q09", "model": "fileApp.gridcell"}, {"fields": {}, "pk": "Q10", "model": "fileApp.gridcell"}, {"fields": {}, "pk": "Q11", "model": "fileApp.gridcell"}, {"fields": {}, "pk": "Q12", "model": "fileApp.gridcell"}, {"fields": {}, "pk": "Q13", "model": "fileApp.gridcell"}, {"fields": {}, "pk": "Q14", "model": "fileApp.gridcell"}, {"fields": {}, "pk": "Q15", "model": "fileApp.gridcell"}, {"fields": {}, "pk": "Q16", "model": "fileApp.gridcell"}, {"fields": {}, "pk": "Q17", "model": "fileApp.gridcell"}, {"fields": {}, "pk": "Q18", "model": "fileApp.gridcell"}, {"fields": {}, "pk": "Q19", "model": "fileApp.gridcell"}, {"fields": {}, "pk": "Q20", "model": "fileApp.gridcell"}, {"fields": {}, "pk": "Q21", "model": "fileApp.gridcell"}, {"fields": {}, "pk": "Q22", "model": "fileApp.gridcell"}, {"fields": {}, "pk": "Q23", "model": "fileApp.gridcell"}, {"fields": {}, "pk": "Q24", "model": "fileApp.gridcell"}, {"fields": {}, "pk": "Q25", "model": "fileApp.gridcell"}, {"fields": {}, "pk": "Q26", "model": "fileApp.gridcell"}, {"fields": {}, "pk": "Q27", "model": "fileApp.gridcell"}, {"fields": {}, "pk": "Q28", "model": "fileApp.gridcell"}, {"fields": {}, "pk": "Q29", "model": "fileApp.gridcell"}, {"fields": {}, "pk": "Q30", "model": "fileApp.gridcell"}, {"fields": {}, "pk": "Q31", "model": "fileApp.gridcell"}, {"fields": {}, "pk": "Q32", "model": "fileApp.gridcell"}, {"fields": {}, "pk": "Q33", "model": "fileApp.gridcell"}, {"fields": {}, "pk": "Q34", "model": "fileApp.gridcell"}, {"fields": {}, "pk": "Q35", "model": "fileApp.gridcell"}, {"fields": {}, "pk": "Q36", "model": "fileApp.gridcell"}, {"fields": {}, "pk": "Q37", "model": "fileApp.gridcell"}, {"fields": {}, "pk": "Q38", "model": "fileApp.gridcell"}, {"fields": {}, "pk": "Q39", "model": "fileApp.gridcell"}, {"fields": {}, "pk": "Q40", "model": "fileApp.gridcell"}, {"fields": {}, "pk": "Q41", "model": "fileApp.gridcell"}, {"fields": {}, "pk": "Q42", "model": "fileApp.gridcell"}, {"fields": {}, "pk": "Q43", "model": "fileApp.gridcell"}, {"fields": {}, "pk": "Q44", "model": "fileApp.gridcell"}, {"fields": {}, "pk": "R01", "model": "fileApp.gridcell"}, {"fields": {}, "pk": "R02", "model": "fileApp.gridcell"}, {"fields": {}, "pk": "R03", "model": "fileApp.gridcell"}, {"fields": {}, "pk": "R04", "model": "fileApp.gridcell"}, {"fields": {}, "pk": "R05", "model": "fileApp.gridcell"}, {"fields": {}, "pk": "R06", "model": "fileApp.gridcell"}, {"fields": {}, "pk": "R07", "model": "fileApp.gridcell"}, {"fields": {}, "pk": "R08", "model": "fileApp.gridcell"}, {"fields": {}, "pk": "R09", "model": "fileApp.gridcell"}, {"fields": {}, "pk": "R10", "model": "fileApp.gridcell"}, {"fields": {}, "pk": "R11", "model": "fileApp.gridcell"}, {"fields": {}, "pk": "R12", "model": "fileApp.gridcell"}, {"fields": {}, "pk": "R13", "model": "fileApp.gridcell"}, {"fields": {}, "pk": "R14", "model": "fileApp.gridcell"}, {"fields": {}, "pk": "R15", "model": "fileApp.gridcell"}, {"fields": {}, "pk": "R16", "model": "fileApp.gridcell"}, {"fields": {}, "pk": "R17", "model": "fileApp.gridcell"}, {"fields": {}, "pk": "R18", "model": "fileApp.gridcell"}, {"fields": {}, "pk": "R19", "model": "fileApp.gridcell"}, {"fields": {}, "pk": "R20", "model": "fileApp.gridcell"}, {"fields": {}, "pk": "R21", "model": "fileApp.gridcell"}, {"fields": {}, "pk": "R22", "model": "fileApp.gridcell"}, {"fields": {}, "pk": "R23", "model": "fileApp.gridcell"}, {"fields": {}, "pk": "R24", "model": "fileApp.gridcell"}, {"fields": {}, "pk": "R25", "model": "fileApp.gridcell"}, {"fields": {}, "pk": "R26", "model": "fileApp.gridcell"}, {"fields": {}, "pk": "R27", "model": "fileApp.gridcell"}, {"fields": {}, "pk": "R28", "model": "fileApp.gridcell"}, {"fields": {}, "pk": "R29", "model": "fileApp.gridcell"}, {"fields": {}, "pk": "R30", "model": "fileApp.gridcell"}, {"fields": {}, "pk": "R31", "model": "fileApp.gridcell"}, {"fields": {}, "pk": "R32", "model": "fileApp.gridcell"}, {"fields": {}, "pk": "R33", "model": "fileApp.gridcell"}, {"fields": {}, "pk": "R34", "model": "fileApp.gridcell"}, {"fields": {}, "pk": "R35", "model": "fileApp.gridcell"}, {"fields": {}, "pk": "R36", "model": "fileApp.gridcell"}, {"fields": {}, "pk": "R37", "model": "fileApp.gridcell"}, {"fields": {}, "pk": "R38", "model": "fileApp.gridcell"}, {"fields": {}, "pk": "R39", "model": "fileApp.gridcell"}, {"fields": {}, "pk": "R40", "model": "fileApp.gridcell"}, {"fields": {}, "pk": "R41", "model": "fileApp.gridcell"}, {"fields": {}, "pk": "R42", "model": "fileApp.gridcell"}, {"fields": {}, "pk": "R43", "model": "fileApp.gridcell"}, {"fields": {}, "pk": "R44", "model": "fileApp.gridcell"}, {"fields": {}, "pk": "S01", "model": "fileApp.gridcell"}, {"fields": {}, "pk": "S02", "model": "fileApp.gridcell"}, {"fields": {}, "pk": "S03", "model": "fileApp.gridcell"}, {"fields": {}, "pk": "S04", "model": "fileApp.gridcell"}, {"fields": {}, "pk": "S05", "model": "fileApp.gridcell"}, {"fields": {}, "pk": "S06", "model": "fileApp.gridcell"}, {"fields": {}, "pk": "S07", "model": "fileApp.gridcell"}, {"fields": {}, "pk": "S08", "model": "fileApp.gridcell"}, {"fields": {}, "pk": "S09", "model": "fileApp.gridcell"}, {"fields": {}, "pk": "S10", "model": "fileApp.gridcell"}, {"fields": {}, "pk": "S11", "model": "fileApp.gridcell"}, {"fields": {}, "pk": "S12", "model": "fileApp.gridcell"}, {"fields": {}, "pk": "S13", "model": "fileApp.gridcell"}, {"fields": {}, "pk": "S14", "model": "fileApp.gridcell"}, {"fields": {}, "pk": "S15", "model": "fileApp.gridcell"}, {"fields": {}, "pk": "S16", "model": "fileApp.gridcell"}, {"fields": {}, "pk": "S17", "model": "fileApp.gridcell"}, {"fields": {}, "pk": "S18", "model": "fileApp.gridcell"}, {"fields": {}, "pk": "S19", "model": "fileApp.gridcell"}, {"fields": {}, "pk": "S20", "model": "fileApp.gridcell"}, {"fields": {}, "pk": "S21", "model": "fileApp.gridcell"}, {"fields": {}, "pk": "S22", "model": "fileApp.gridcell"}, {"fields": {}, "pk": "S23", "model": "fileApp.gridcell"}, {"fields": {}, "pk": "S24", "model": "fileApp.gridcell"}, {"fields": {}, "pk": "S25", "model": "fileApp.gridcell"}, {"fields": {}, "pk": "S26", "model": "fileApp.gridcell"}, {"fields": {}, "pk": "S27", "model": "fileApp.gridcell"}, {"fields": {}, "pk": "S28", "model": "fileApp.gridcell"}, {"fields": {}, "pk": "S29", "model": "fileApp.gridcell"}, {"fields": {}, "pk": "S30", "model": "fileApp.gridcell"}, {"fields": {}, "pk": "S31", "model": "fileApp.gridcell"}, {"fields": {}, "pk": "S32", "model": "fileApp.gridcell"}, {"fields": {}, "pk": "S33", "model": "fileApp.gridcell"}, {"fields": {}, "pk": "S34", "model": "fileApp.gridcell"}, {"fields": {}, "pk": "S35", "model": "fileApp.gridcell"}, {"fields": {}, "pk": "S36", "model": "fileApp.gridcell"}, {"fields": {}, "pk": "S37", "model": "fileApp.gridcell"}, {"fields": {}, "pk": "S38", "model": "fileApp.gridcell"}, {"fields": {}, "pk": "S39", "model": "fileApp.gridcell"}, {"fields": {}, "pk": "S40", "model": "fileApp.gridcell"}, {"fields": {}, "pk": "S41", "model": "fileApp.gridcell"}, {"fields": {}, "pk": "S42", "model": "fileApp.gridcell"}, {"fields": {}, "pk": "S43", "model": "fileApp.gridcell"}, {"fields": {}, "pk": "S44", "model": "fileApp.gridcell"}, {"fields": {}, "pk": "T01", "model": "fileApp.gridcell"}, {"fields": {}, "pk": "T02", "model": "fileApp.gridcell"}, {"fields": {}, "pk": "T03", "model": "fileApp.gridcell"}, {"fields": {}, "pk": "T04", "model": "fileApp.gridcell"}, {"fields": {}, "pk": "T05", "model": "fileApp.gridcell"}, {"fields": {}, "pk": "T06", "model": "fileApp.gridcell"}, {"fields": {}, "pk": "T07", "model": "fileApp.gridcell"}, {"fields": {}, "pk": "T08", "model": "fileApp.gridcell"}, {"fields": {}, "pk": "T09", "model": "fileApp.gridcell"}, {"fields": {}, "pk": "T10", "model": "fileApp.gridcell"}, {"fields": {}, "pk": "T11", "model": "fileApp.gridcell"}, {"fields": {}, "pk": "T12", "model": "fileApp.gridcell"}, {"fields": {}, "pk": "T13", "model": "fileApp.gridcell"}, {"fields": {}, "pk": "T14", "model": "fileApp.gridcell"}, {"fields": {}, "pk": "T15", "model": "fileApp.gridcell"}, {"fields": {}, "pk": "T16", "model": "fileApp.gridcell"}, {"fields": {}, "pk": "T17", "model": "fileApp.gridcell"}, {"fields": {}, "pk": "T18", "model": "fileApp.gridcell"}, {"fields": {}, "pk": "T19", "model": "fileApp.gridcell"}, {"fields": {}, "pk": "T20", "model": "fileApp.gridcell"}, {"fields": {}, "pk": "T21", "model": "fileApp.gridcell"}, {"fields": {}, "pk": "T22", "model": "fileApp.gridcell"}, {"fields": {}, "pk": "T23", "model": "fileApp.gridcell"}, {"fields": {}, "pk": "T24", "model": "fileApp.gridcell"}, {"fields": {}, "pk": "T25", "model": "fileApp.gridcell"}, {"fields": {}, "pk": "T26", "model": "fileApp.gridcell"}, {"fields": {}, "pk": "T27", "model": "fileApp.gridcell"}, {"fields": {}, "pk": "T28", "model": "fileApp.gridcell"}, {"fields": {}, "pk": "T29", "model": "fileApp.gridcell"}, {"fields": {}, "pk": "T30", "model": "fileApp.gridcell"}, {"fields": {}, "pk": "T31", "model": "fileApp.gridcell"}, {"fields": {}, "pk": "T32", "model": "fileApp.gridcell"}, {"fields": {}, "pk": "T33", "model": "fileApp.gridcell"}, {"fields": {}, "pk": "T34", "model": "fileApp.gridcell"}, {"fields": {}, "pk": "T35", "model": "fileApp.gridcell"}, {"fields": {}, "pk": "T36", "model": "fileApp.gridcell"}, {"fields": {}, "pk": "T37", "model": "fileApp.gridcell"}, {"fields": {}, "pk": "T39", "model": "fileApp.gridcell"}, {"fields": {}, "pk": "T40", "model": "fileApp.gridcell"}, {"fields": {}, "pk": "T41", "model": "fileApp.gridcell"}, {"fields": {}, "pk": "T42", "model": "fileApp.gridcell"}, {"fields": {}, "pk": "T43", "model": "fileApp.gridcell"}, {"fields": {}, "pk": "T44", "model": "fileApp.gridcell"}, {"fields": {}, "pk": "U01", "model": "fileApp.gridcell"}, {"fields": {}, "pk": "U02", "model": "fileApp.gridcell"}, {"fields": {}, "pk": "U03", "model": "fileApp.gridcell"}, {"fields": {}, "pk": "U04", "model": "fileApp.gridcell"}, {"fields": {}, "pk": "U05", "model": "fileApp.gridcell"}, {"fields": {}, "pk": "U06", "model": "fileApp.gridcell"}, {"fields": {}, "pk": "U07", "model": "fileApp.gridcell"}, {"fields": {}, "pk": "U08", "model": "fileApp.gridcell"}, {"fields": {}, "pk": "U09", "model": "fileApp.gridcell"}, {"fields": {}, "pk": "U10", "model": "fileApp.gridcell"}, {"fields": {}, "pk": "U11", "model": "fileApp.gridcell"}, {"fields": {}, "pk": "U12", "model": "fileApp.gridcell"}, {"fields": {}, "pk": "U13", "model": "fileApp.gridcell"}, {"fields": {}, "pk": "U14", "model": "fileApp.gridcell"}, {"fields": {}, "pk": "U15", "model": "fileApp.gridcell"}, {"fields": {}, "pk": "U16", "model": "fileApp.gridcell"}, {"fields": {}, "pk": "U17", "model": "fileApp.gridcell"}, {"fields": {}, "pk": "U18", "model": "fileApp.gridcell"}, {"fields": {}, "pk": "U19", "model": "fileApp.gridcell"}, {"fields": {}, "pk": "U20", "model": "fileApp.gridcell"}, {"fields": {}, "pk": "U21", "model": "fileApp.gridcell"}, {"fields": {}, "pk": "U22", "model": "fileApp.gridcell"}, {"fields": {}, "pk": "U23", "model": "fileApp.gridcell"}, {"fields": {}, "pk": "U24", "model": "fileApp.gridcell"}, {"fields": {}, "pk": "U25", "model": "fileApp.gridcell"}, {"fields": {}, "pk": "U26", "model": "fileApp.gridcell"}, {"fields": {}, "pk": "U27", "model": "fileApp.gridcell"}, {"fields": {}, "pk": "U28", "model": "fileApp.gridcell"}, {"fields": {}, "pk": "U29", "model": "fileApp.gridcell"}, {"fields": {}, "pk": "U31", "model": "fileApp.gridcell"}, {"fields": {}, "pk": "U32", "model": "fileApp.gridcell"}, {"fields": {}, "pk": "U33", "model": "fileApp.gridcell"}, {"fields": {}, "pk": "U34", "model": "fileApp.gridcell"}, {"fields": {}, "pk": "U35", "model": "fileApp.gridcell"}, {"fields": {}, "pk": "U36", "model": "fileApp.gridcell"}, {"fields": {}, "pk": "U37", "model": "fileApp.gridcell"}, {"fields": {}, "pk": "U38", "model": "fileApp.gridcell"}, {"fields": {}, "pk": "U39", "model": "fileApp.gridcell"}, {"fields": {}, "pk": "U40", "model": "fileApp.gridcell"}, {"fields": {}, "pk": "U41", "model": "fileApp.gridcell"}, {"fields": {}, "pk": "U42", "model": "fileApp.gridcell"}, {"fields": {}, "pk": "U43", "model": "fileApp.gridcell"}, {"fields": {}, "pk": "U44", "model": "fileApp.gridcell"}, {"fields": {}, "pk": "V01", "model": "fileApp.gridcell"}, {"fields": {}, "pk": "V02", "model": "fileApp.gridcell"}, {"fields": {}, "pk": "V03", "model": "fileApp.gridcell"}, {"fields": {}, "pk": "V04", "model": "fileApp.gridcell"}, {"fields": {}, "pk": "V05", "model": "fileApp.gridcell"}, {"fields": {}, "pk": "V06", "model": "fileApp.gridcell"}, {"fields": {}, "pk": "V07", "model": "fileApp.gridcell"}, {"fields": {}, "pk": "V08", "model": "fileApp.gridcell"}, {"fields": {}, "pk": "V09", "model": "fileApp.gridcell"}, {"fields": {}, "pk": "V10", "model": "fileApp.gridcell"}, {"fields": {}, "pk": "V11", "model": "fileApp.gridcell"}, {"fields": {}, "pk": "V12", "model": "fileApp.gridcell"}, {"fields": {}, "pk": "V13", "model": "fileApp.gridcell"}, {"fields": {}, "pk": "V14", "model": "fileApp.gridcell"}, {"fields": {}, "pk": "V15", "model": "fileApp.gridcell"}, {"fields": {}, "pk": "V16", "model": "fileApp.gridcell"}, {"fields": {}, "pk": "V17", "model": "fileApp.gridcell"}, {"fields": {}, "pk": "V18", "model": "fileApp.gridcell"}, {"fields": {}, "pk": "V19", "model": "fileApp.gridcell"}, {"fields": {}, "pk": "V20", "model": "fileApp.gridcell"}, {"fields": {}, "pk": "V21", "model": "fileApp.gridcell"}, {"fields": {}, "pk": "V22", "model": "fileApp.gridcell"}, {"fields": {}, "pk": "V23", "model": "fileApp.gridcell"}, {"fields": {}, "pk": "V24", "model": "fileApp.gridcell"}, {"fields": {}, "pk": "V25", "model": "fileApp.gridcell"}, {"fields": {}, "pk": "V26", "model": "fileApp.gridcell"}, {"fields": {}, "pk": "V27", "model": "fileApp.gridcell"}, {"fields": {}, "pk": "V28", "model": "fileApp.gridcell"}, {"fields": {}, "pk": "V29", "model": "fileApp.gridcell"}, {"fields": {}, "pk": "V30", "model": "fileApp.gridcell"}, {"fields": {}, "pk": "V31", "model": "fileApp.gridcell"}, {"fields": {}, "pk": "V32", "model": "fileApp.gridcell"}, {"fields": {}, "pk": "V33", "model": "fileApp.gridcell"}, {"fields": {}, "pk": "V34", "model": "fileApp.gridcell"}, {"fields": {}, "pk": "V35", "model": "fileApp.gridcell"}, {"fields": {}, "pk": "V36", "model": "fileApp.gridcell"}, {"fields": {}, "pk": "V37", "model": "fileApp.gridcell"}, {"fields": {}, "pk": "V38", "model": "fileApp.gridcell"}, {"fields": {}, "pk": "V39", "model": "fileApp.gridcell"}, {"fields": {}, "pk": "V40", "model": "fileApp.gridcell"}, {"fields": {}, "pk": "V41", "model": "fileApp.gridcell"}, {"fields": {}, "pk": "V42", "model": "fileApp.gridcell"}, {"fields": {}, "pk": "V43", "model": "fileApp.gridcell"}, {"fields": {}, "pk": "V44", "model": "fileApp.gridcell"}, {"fields": {}, "pk": "W01", "model": "fileApp.gridcell"}, {"fields": {}, "pk": "W02", "model": "fileApp.gridcell"}, {"fields": {}, "pk": "W03", "model": "fileApp.gridcell"}, {"fields": {}, "pk": "W04", "model": "fileApp.gridcell"}, {"fields": {}, "pk": "W05", "model": "fileApp.gridcell"}, {"fields": {}, "pk": "W06", "model": "fileApp.gridcell"}, {"fields": {}, "pk": "W07", "model": "fileApp.gridcell"}, {"fields": {}, "pk": "W08", "model": "fileApp.gridcell"}, {"fields": {}, "pk": "W09", "model": "fileApp.gridcell"}, {"fields": {}, "pk": "W10", "model": "fileApp.gridcell"}, {"fields": {}, "pk": "W11", "model": "fileApp.gridcell"}, {"fields": {}, "pk": "W12", "model": "fileApp.gridcell"}, {"fields": {}, "pk": "W13", "model": "fileApp.gridcell"}, {"fields": {}, "pk": "W14", "model": "fileApp.gridcell"}, {"fields": {}, "pk": "W15", "model": "fileApp.gridcell"}, {"fields": {}, "pk": "W16", "model": "fileApp.gridcell"}, {"fields": {}, "pk": "W17", "model": "fileApp.gridcell"}, {"fields": {}, "pk": "W18", "model": "fileApp.gridcell"}, {"fields": {}, "pk": "W19", "model": "fileApp.gridcell"}, {"fields": {}, "pk": "W20", "model": "fileApp.gridcell"}, {"fields": {}, "pk": "W21", "model": "fileApp.gridcell"}, {"fields": {}, "pk": "W22", "model": "fileApp.gridcell"}, {"fields": {}, "pk": "W23", "model": "fileApp.gridcell"}, {"fields": {}, "pk": "W24", "model": "fileApp.gridcell"}, {"fields": {}, "pk": "W25", "model": "fileApp.gridcell"}, {"fields": {}, "pk": "W26", "model": "fileApp.gridcell"}, {"fields": {}, "pk": "W27", "model": "fileApp.gridcell"}, {"fields": {}, "pk": "W28", "model": "fileApp.gridcell"}, {"fields": {}, "pk": "W29", "model": "fileApp.gridcell"}, {"fields": {}, "pk": "W30", "model": "fileApp.gridcell"}, {"fields": {}, "pk": "W31", "model": "fileApp.gridcell"}, {"fields": {}, "pk": "W32", "model": "fileApp.gridcell"}, {"fields": {}, "pk": "W33", "model": "fileApp.gridcell"}, {"fields": {}, "pk": "W34", "model": "fileApp.gridcell"}, {"fields": {}, "pk": "W35", "model": "fileApp.gridcell"}, {"fields": {}, "pk": "W36", "model": "fileApp.gridcell"}, {"fields": {}, "pk": "W37", "model": "fileApp.gridcell"}, {"fields": {}, "pk": "W38", "model": "fileApp.gridcell"}, {"fields": {}, "pk": "W39", "model": "fileApp.gridcell"}, {"fields": {}, "pk": "W40", "model": "fileApp.gridcell"}, {"fields": {}, "pk": "W41", "model": "fileApp.gridcell"}, {"fields": {}, "pk": "W42", "model": "fileApp.gridcell"}, {"fields": {}, "pk": "W43", "model": "fileApp.gridcell"}, {"fields": {}, "pk": "W44", "model": "fileApp.gridcell"}, {"fields": {}, "pk": "X01", "model": "fileApp.gridcell"}, {"fields": {}, "pk": "X02", "model": "fileApp.gridcell"}, {"fields": {}, "pk": "X03", "model": "fileApp.gridcell"}, {"fields": {}, "pk": "X04", "model": "fileApp.gridcell"}, {"fields": {}, "pk": "X05", "model": "fileApp.gridcell"}, {"fields": {}, "pk": "X06", "model": "fileApp.gridcell"}, {"fields": {}, "pk": "X07", "model": "fileApp.gridcell"}, {"fields": {}, "pk": "X08", "model": "fileApp.gridcell"}, {"fields": {}, "pk": "X09", "model": "fileApp.gridcell"}, {"fields": {}, "pk": "X10", "model": "fileApp.gridcell"}, {"fields": {}, "pk": "X11", "model": "fileApp.gridcell"}, {"fields": {}, "pk": "X12", "model": "fileApp.gridcell"}, {"fields": {}, "pk": "X13", "model": "fileApp.gridcell"}, {"fields": {}, "pk": "X14", "model": "fileApp.gridcell"}, {"fields": {}, "pk": "X15", "model": "fileApp.gridcell"}, {"fields": {}, "pk": "X16", "model": "fileApp.gridcell"}, {"fields": {}, "pk": "X17", "model": "fileApp.gridcell"}, {"fields": {}, "pk": "X18", "model": "fileApp.gridcell"}, {"fields": {}, "pk": "X19", "model": "fileApp.gridcell"}, {"fields": {}, "pk": "X20", "model": "fileApp.gridcell"}, {"fields": {}, "pk": "X21", "model": "fileApp.gridcell"}, {"fields": {}, "pk": "X22", "model": "fileApp.gridcell"}, {"fields": {}, "pk": "X23", "model": "fileApp.gridcell"}, {"fields": {}, "pk": "X24", "model": "fileApp.gridcell"}, {"fields": {}, "pk": "X25", "model": "fileApp.gridcell"}, {"fields": {}, "pk": "X26", "model": "fileApp.gridcell"}, {"fields": {}, "pk": "X27", "model": "fileApp.gridcell"}, {"fields": {}, "pk": "X28", "model": "fileApp.gridcell"}, {"fields": {}, "pk": "X29", "model": "fileApp.gridcell"}, {"fields": {}, "pk": "X30", "model": "fileApp.gridcell"}, {"fields": {}, "pk": "X31", "model": "fileApp.gridcell"}, {"fields": {}, "pk": "X32", "model": "fileApp.gridcell"}, {"fields": {}, "pk": "X33", "model": "fileApp.gridcell"}, {"fields": {}, "pk": "X34", "model": "fileApp.gridcell"}, {"fields": {}, "pk": "X35", "model": "fileApp.gridcell"}, {"fields": {}, "pk": "X36", "model": "fileApp.gridcell"}, {"fields": {}, "pk": "X37", "model": "fileApp.gridcell"}, {"fields": {}, "pk": "X38", "model": "fileApp.gridcell"}, {"fields": {}, "pk": "X39", "model": "fileApp.gridcell"}, {"fields": {}, "pk": "X40", "model": "fileApp.gridcell"}, {"fields": {}, "pk": "X41", "model": "fileApp.gridcell"}, {"fields": {}, "pk": "X42", "model": "fileApp.gridcell"}, {"fields": {}, "pk": "X43", "model": "fileApp.gridcell"}, {"fields": {}, "pk": "X44", "model": "fileApp.gridcell"}, {"fields": {}, "pk": "Y01", "model": "fileApp.gridcell"}, {"fields": {}, "pk": "Y02", "model": "fileApp.gridcell"}, {"fields": {}, "pk": "Y03", "model": "fileApp.gridcell"}, {"fields": {}, "pk": "Y04", "model": "fileApp.gridcell"}, {"fields": {}, "pk": "Y05", "model": "fileApp.gridcell"}, {"fields": {}, "pk": "Y06", "model": "fileApp.gridcell"}, {"fields": {}, "pk": "Y07", "model": "fileApp.gridcell"}, {"fields": {}, "pk": "Y08", "model": "fileApp.gridcell"}, {"fields": {}, "pk": "Y09", "model": "fileApp.gridcell"}, {"fields": {}, "pk": "Y10", "model": "fileApp.gridcell"}, {"fields": {}, "pk": "Y11", "model": "fileApp.gridcell"}, {"fields": {}, "pk": "Y12", "model": "fileApp.gridcell"}, {"fields": {}, "pk": "Y13", "model": "fileApp.gridcell"}, {"fields": {}, "pk": "Y14", "model": "fileApp.gridcell"}, {"fields": {}, "pk": "Y15", "model": "fileApp.gridcell"}, {"fields": {}, "pk": "Y16", "model": "fileApp.gridcell"}, {"fields": {}, "pk": "Y17", "model": "fileApp.gridcell"}, {"fields": {}, "pk": "Y18", "model": "fileApp.gridcell"}, {"fields": {}, "pk": "Y19", "model": "fileApp.gridcell"}, {"fields": {}, "pk": "Y20", "model": "fileApp.gridcell"}, {"fields": {}, "pk": "Y21", "model": "fileApp.gridcell"}, {"fields": {}, "pk": "Y22", "model": "fileApp.gridcell"}, {"fields": {}, "pk": "Y23", "model": "fileApp.gridcell"}, {"fields": {}, "pk": "Y24", "model": "fileApp.gridcell"}, {"fields": {}, "pk": "Y25", "model": "fileApp.gridcell"}, {"fields": {}, "pk": "Y26", "model": "fileApp.gridcell"}, {"fields": {}, "pk": "Y27", "model": "fileApp.gridcell"}, {"fields": {}, "pk": "Y28", "model": "fileApp.gridcell"}, {"fields": {}, "pk": "Y29", "model": "fileApp.gridcell"}, {"fields": {}, "pk": "Y30", "model": "fileApp.gridcell"}, {"fields": {}, "pk": "Y31", "model": "fileApp.gridcell"}, {"fields": {}, "pk": "Y32", "model": "fileApp.gridcell"}, {"fields": {}, "pk": "Y33", "model": "fileApp.gridcell"}, {"fields": {}, "pk": "Y34", "model": "fileApp.gridcell"}, {"fields": {}, "pk": "Y35", "model": "fileApp.gridcell"}, {"fields": {}, "pk": "Y36", "model": "fileApp.gridcell"}]